{
	"cmake" : 
	{
		"generator" : 
		{
			"multiConfig" : false,
			"name" : "Ninja"
		},
		"paths" : 
		{
			"cmake" : "/Users/danielpalmor/Desktop/CLion.app/Contents/bin/cmake/mac/bin/cmake",
			"cpack" : "/Users/danielpalmor/Desktop/CLion.app/Contents/bin/cmake/mac/bin/cpack",
			"ctest" : "/Users/danielpalmor/Desktop/CLion.app/Contents/bin/cmake/mac/bin/ctest",
			"root" : "/Users/danielpalmor/Desktop/CLion.app/Contents/bin/cmake/mac/share/cmake-3.23"
		},
		"version" : 
		{
			"isDirty" : false,
			"major" : 3,
			"minor" : 23,
			"patch" : 2,
			"string" : "3.23.2",
			"suffix" : ""
		}
	},
	"objects" : 
	[
		{
			"jsonFile" : "codemodel-v2-c448b19e6d9cfa1484b7.json",
			"kind" : "codemodel",
			"version" : 
			{
				"major" : 2,
				"minor" : 4
			}
		},
		{
			"jsonFile" : "cache-v2-47ab0dc7cf929b4ddd15.json",
			"kind" : "cache",
			"version" : 
			{
				"major" : 2,
				"minor" : 0
			}
		},
		{
			"jsonFile" : "cmakeFiles-v1-b99237a951f141ad72ee.json",
			"kind" : "cmakeFiles",
			"version" : 
			{
				"major" : 1,
				"minor" : 0
			}
		},
		{
			"jsonFile" : "toolchains-v1-ae04bbe1f607ca07f0b7.json",
			"kind" : "toolchains",
			"version" : 
			{
				"major" : 1,
				"minor" : 0
			}
		}
	],
	"reply" : 
	{
		"cache-v2" : 
		{
			"jsonFile" : "cache-v2-47ab0dc7cf929b4ddd15.json",
			"kind" : "cache",
			"version" : 
			{
				"major" : 2,
				"minor" : 0
			}
		},
		"cmakeFiles-v1" : 
		{
			"jsonFile" : "cmakeFiles-v1-b99237a951f141ad72ee.json",
			"kind" : "cmakeFiles",
			"version" : 
			{
				"major" : 1,
				"minor" : 0
			}
		},
		"codemodel-v2" : 
		{
			"jsonFile" : "codemodel-v2-c448b19e6d9cfa1484b7.json",
			"kind" : "codemodel",
			"version" : 
			{
				"major" : 2,
				"minor" : 4
			}
		},
		"toolchains-v1" : 
		{
			"jsonFile" : "toolchains-v1-ae04bbe1f607ca07f0b7.json",
			"kind" : "toolchains",
			"version" : 
			{
				"major" : 1,
				"minor" : 0
			}
		}
	}
}
